.gitignore
LICENSE
README.md
main.py
requirements.txt
setup.py
docs/Makefile
docs/make.bat
docs/source/conf.py
docs/source/index.rst
docs/source/modules.rst
docs/source/mssqlantipathy.rst
sqlantipathy/__init__.py
sqlantipathy/mssqlantipathy.py
sqlantipathy/sqlantipathy.py
sqlantipathy.egg-info/PKG-INFO
sqlantipathy.egg-info/SOURCES.txt
sqlantipathy.egg-info/dependency_links.txt
sqlantipathy.egg-info/not-zip-safe
sqlantipathy.egg-info/requires.txt
sqlantipathy.egg-info/top_level.txt