Metadata-Version: 2.1
Name: sqlantipathy
Version: 0.0.71
Summary: Python library to work with SQL DB
Home-page: https://github.com/pietrogiuffrida/sqlantipathy/
Author: Pietro Giuffrida
Author-email: pietro.giuffri@gmail.com
License: MIT
Platform: UNKNOWN
Classifier: Programming Language :: Python :: 3
Classifier: License :: OSI Approved :: MIT License
Classifier: Operating System :: OS Independent
Classifier: Development Status :: 3 - Alpha
